{
  "placeName": "Alan Cross Portfolio",
  "averageRating": 4.9,
  "userRatingCount": 328,
  "reviews": [
    {
      "id": "demo-review-01",
      "rating": 5,
      "text": "Outstanding experience from start to finish. Communication was clear, the final website looked great, and updates were easy to request.",
      "languageCode": "en",
      "relativePublishTimeDescription": "2 weeks ago",
      "publishTime": "2026-02-07T10:21:00Z",
      "author": {
        "name": "Amelia Rivera",
        "avatarUrl": "https://i.pravatar.cc/150?img=32"
      }
    },
    {
      "id": "demo-review-02",
      "rating": 5,
      "text": "The quality of work is consistently high. Fast turnaround, thoughtful design choices, and a smooth handover process.",
      "languageCode": "en",
      "relativePublishTimeDescription": "3 weeks ago",
      "publishTime": "2026-01-31T14:09:00Z",
      "author": {
        "name": "Noah Kim",
        "avatarUrl": "https://i.pravatar.cc/150?img=12"
      }
    },
    {
      "id": "demo-review-03",
      "rating": 5,
      "text": "Professional, friendly, and detail-focused. The project stayed on track and the finished portfolio site exceeded expectations.",
      "languageCode": "en",
      "relativePublishTimeDescription": "1 month ago",
      "publishTime": "2026-01-19T18:44:00Z",
      "author": {
        "name": "Priya Desai",
        "avatarUrl": "https://i.pravatar.cc/150?img=47"
      }
    },
    {
      "id": "demo-review-04",
      "rating": 4,
      "text": "Great collaboration and very responsive support. A couple of revisions took longer than expected, but the final result was excellent.",
      "languageCode": "en",
      "relativePublishTimeDescription": "1 month ago",
      "publishTime": "2026-01-11T11:33:00Z",
      "author": {
        "name": "Lucas Bennett",
        "avatarUrl": "https://i.pravatar.cc/150?img=15"
      }
    },
    {
      "id": "demo-review-05",
      "rating": 5,
      "text": "Incredible attention to detail. The structure, content layout, and visual polish all came together really well.",
      "languageCode": "en",
      "relativePublishTimeDescription": "2 months ago",
      "publishTime": "2025-12-27T09:16:00Z",
      "author": {
        "name": "Sofia Morales",
        "avatarUrl": "https://i.pravatar.cc/150?img=25"
      }
    },
    {
      "id": "demo-review-06",
      "rating": 5,
      "text": "Five stars for consistency alone. Strong delivery, clear communication, and reliable follow-through throughout the whole build.",
      "languageCode": "en",
      "relativePublishTimeDescription": "2 months ago",
      "publishTime": "2025-12-14T08:52:00Z",
      "author": {
        "name": "Ethan Walsh",
        "avatarUrl": "https://i.pravatar.cc/150?img=8"
      }
    },
    {
      "id": "demo-review-07",
      "rating": 5,
      "text": "Absolutely loved working together. Feedback was handled quickly and every requested change was implemented accurately.",
      "languageCode": "en",
      "relativePublishTimeDescription": "3 months ago",
      "publishTime": "2025-11-30T19:05:00Z",
      "author": {
        "name": "Chloe Nguyen",
        "avatarUrl": "https://i.pravatar.cc/150?img=44"
      }
    },
    {
      "id": "demo-review-08",
      "rating": 4,
      "text": "Really positive experience with polished presentation and thoughtful implementation. Overall, a strong result.",
      "languageCode": "en",
      "relativePublishTimeDescription": "4 months ago",
      "publishTime": "2025-10-20T13:28:00Z",
      "author": {
        "name": "Marcus Patel",
        "avatarUrl": "https://i.pravatar.cc/150?img=19"
      }
    }
  ]
}
